otter_service_stdalone/__init__.py
otter_service_stdalone/access_sops_keys.py
otter_service_stdalone/app.py
otter_service_stdalone/fs_logging.py
otter_service_stdalone/grade_notebooks.py
otter_service_stdalone/index.html
otter_service_stdalone/upload_handle.py
otter_service_stdalone/user_auth.py
otter_service_stdalone/util.py
otter_service_stdalone/scripts/web_socket.js
otter_service_stdalone/secrets/gh_key.dev.yaml
otter_service_stdalone/secrets/gh_key.local.yaml
otter_service_stdalone/secrets/gh_key.prod.yaml
otter_service_stdalone/secrets/gh_key.staging.yaml
otter_service_stdalone/static_files/README_DO_NOT_DISTRIBUTE.txt
otter_service_stdalone/static_templates/403.html
otter_service_stdalone/static_templates/500.html
otter_service_stdalone-1.1.36.dist-info/METADATA
otter_service_stdalone-1.1.36.dist-info/WHEEL
otter_service_stdalone-1.1.36.dist-info/entry_points.txt
otter_service_stdalone-1.1.36.dist-info/top_level.txt
otter_service_stdalone-1.1.36.dist-info/RECORD
