Metadata-Version: 2.4
Name: otter_service_stdalone
Version: 1.1.36
Summary: Grading Service for Instructors using Otter Grader
Home-page: https://github.com/sean-morris/otter-service-stdalone
Author: Sean Morris
Author-email: sean.smorris@berkeley.edu
Requires-Python: >=3.8
